setup.py
pleercom/__init__.py
pleercom_py.egg-info/PKG-INFO
pleercom_py.egg-info/SOURCES.txt
pleercom_py.egg-info/dependency_links.txt
pleercom_py.egg-info/not-zip-safe
pleercom_py.egg-info/requires.txt
pleercom_py.egg-info/top_level.txt