Metadata-Version: 1.0
Name: pleercom-py
Version: 0.1.1
Summary: Pleer.com API Wrapper
Home-page: https://github.com/amureki/pleercom-py.git
Author: Rustem Sayargaliev
Author-email: r.sayargaliev@gmail.com
License: MIT
Platform: UNKNOWN
